coolwork/__init__.py
coolwork/dccb.py
ywkfirst-2.1.dist-info/METADATA
ywkfirst-2.1.dist-info/WHEEL
ywkfirst-2.1.dist-info/top_level.txt
ywkfirst-2.1.dist-info/RECORD
