Metadata-Version: 2.1
Name: ywkfirst
Version: 2.1
Summary: good job
Home-page: UNKNOWN
Author: UNKNOWN
Author-email: UNKNOWN
License: UNKNOWN
Platform: UNKNOWN
